sharq_models/__init__.py
sharq_models/db/__init__.py
sharq_models/db/base.py
sharq_models/db/config.py
sharq_models/db/get_db.py
sharq_models/models/__init__.py
sharq_models/models/additional_info.py
sharq_models/models/application.py
sharq_models/models/direction.py
sharq_models/models/education_info.py
sharq_models/models/faculty.py
sharq_models/models/passport_data.py
sharq_models/models/specialization.py
sharq_models/models/study_form.py
sharq_models/models/user.py
sharq_models/src/__init__.py
sharq_models/src/db/__init__.py
sharq_models/src/db/base.py
sharq_models/src/db/config.py
sharq_models/src/db/get_db.py
sharq_models/src/models/__init__.py
sharq_models/src/models/additional_info.py
sharq_models/src/models/application.py
sharq_models/src/models/direction.py
sharq_models/src/models/education_info.py
sharq_models/src/models/faculty.py
sharq_models/src/models/passport_data.py
sharq_models/src/models/specialization.py
sharq_models/src/models/study_form.py
sharq_models/src/models/user.py
sharq_models-0.1.1.dist-info/METADATA
sharq_models-0.1.1.dist-info/WHEEL
sharq_models-0.1.1.dist-info/top_level.txt
sharq_models-0.1.1.dist-info/RECORD
